grzegorz/__init__.py
grzegorz/__main__.py
grzegorz/anki_integration.py
grzegorz/fetcher.py
grzegorz/generator.py
grzegorz/io.py
grzegorz/subcommands.py
grzegorz/test.py
grzegorz/word.py
grzegorz/wordlist.py
grzegorz-0.6.1.dist-info/licenses/LICENSE
grzegorz-0.6.1.dist-info/METADATA
grzegorz-0.6.1.dist-info/WHEEL
grzegorz-0.6.1.dist-info/entry_points.txt
grzegorz-0.6.1.dist-info/top_level.txt
grzegorz-0.6.1.dist-info/RECORD
