Metadata-Version: 2.4
Name: grzegorz
Version: 0.6.1
Summary: Minimal pair generator and phonetics tool
Home-page: https://github.com/xylous/grzegorz
Author: xylous
Author-email: xylous.e@gmail.com
Project-URL: Bug Tracker, https://github.com/xylous/grzegorz/issues
Classifier: Programming Language :: Python :: 3
Classifier: License :: OSI Approved :: GNU General Public License v3 (GPLv3)
Classifier: Operating System :: OS Independent
Classifier: Environment :: Console
Classifier: Intended Audience :: Education
Classifier: Topic :: Education
Classifier: Topic :: Text Processing :: Linguistic
Requires-Python: >=3.10
License-File: LICENSE
Requires-Dist: beautifulsoup4
Requires-Dist: tqdm
Requires-Dist: requests
Requires-Dist: genanki
Dynamic: license-file
